certsync/__init__.py
certsync/entry.py
certsync-0.1.6.dist-info/LICENSE
certsync-0.1.6.dist-info/METADATA
certsync-0.1.6.dist-info/WHEEL
certsync-0.1.6.dist-info/entry_points.txt
certsync-0.1.6.dist-info/RECORD
