Metadata-Version: 2.1
Name: certsync
Version: 0.1.6
Summary: Dump NTDS with golden certificates and UnPAC the hash
Home-page: https://github.com/zblurx/certsync
License: MIT
Keywords: ntds,certificate,hashes
Author: zblurx
Author-email: seigneuret.thomas@protonmail.com
Requires-Python: >=3.7,<4.0
Classifier: Environment :: Console
Classifier: License :: OSI Approved :: MIT License
Classifier: Programming Language :: Python :: 3
Classifier: Programming Language :: Python :: 3.7
Classifier: Programming Language :: Python :: 3.8
Classifier: Programming Language :: Python :: 3.9
Classifier: Programming Language :: Python :: 3.10
Classifier: Programming Language :: Python :: 3.11
Classifier: Topic :: Security
Requires-Dist: certipy-ad (>=4.4.0,<5.0.0)
Requires-Dist: tqdm (>=4.64.1,<5.0.0)
Project-URL: Repository, https://github.com/zblurx/certsync
